radcomp/__init__.py
radcomp/common/__init__.py
radcomp/common/prelayer.py
radcomp/common/utils.py
radcomp/common/voiding.py
radcomp/dcm/__init__.py
radcomp/dcm/dcm.py
radcomp/dcm/dcm_internal.py
radcomp/dcm/dcm_read_toml.py
radcomp-0.3.0.dist-info/METADATA
radcomp-0.3.0.dist-info/WHEEL
radcomp-0.3.0.dist-info/licenses/LICENSE
radcomp-0.3.0.dist-info/RECORD
