Metadata-Version: 2.1
Name: radcomp
Version: 0.3.0
Summary: Model the movement of radioactive nuclei and their progeny through a system
Project-URL: Homepage, https://github.com/jakeforster/radcomp
Project-URL: Bug Tracker, https://github.com/jakeforster/radcomp/issues
Project-URL: Documentation, https://radcomp.readthedocs.io
Project-URL: Changelog, https://github.com/jakeforster/radcomp/CHANGELOG.md
Author: Jake Forster
License: MIT
License-File: LICENSE
Classifier: License :: OSI Approved :: MIT License
Classifier: Operating System :: OS Independent
Classifier: Programming Language :: Python :: 3
Classifier: Topic :: Scientific/Engineering :: Medical Science Apps.
Requires-Python: >=3.10
Requires-Dist: matplotlib<4,>=3.5.2
Requires-Dist: numpy<2,>=1.23.2
Requires-Dist: scipy<2,>=1.10.1
